LICENSE
MANIFEST.in
README.md
setup.cfg
setup.py
bin/convert
mgeconvert/__init__.py
mgeconvert/version.py
mgeconvert.egg-info/PKG-INFO
mgeconvert.egg-info/SOURCES.txt
mgeconvert.egg-info/dependency_links.txt
mgeconvert.egg-info/requires.txt
mgeconvert.egg-info/top_level.txt
mgeconvert/backend/__init__.py
mgeconvert/backend/ir_to_caffe/__init__.py
mgeconvert/backend/ir_to_caffe/caffe_converter.py
mgeconvert/backend/ir_to_caffe/caffe_op.py
mgeconvert/backend/ir_to_caffe/init.sh
mgeconvert/backend/ir_to_caffe/caffe_pb/__init__.py
mgeconvert/backend/ir_to_caffe/caffe_pb/caffe_pb2.py
mgeconvert/backend/ir_to_mge/__init__.py
mgeconvert/backend/ir_to_mge/mge_converter.py
mgeconvert/backend/ir_to_mge/mge_op.py
mgeconvert/backend/ir_to_onnx/__init__.py
mgeconvert/backend/ir_to_onnx/init.sh
mgeconvert/backend/ir_to_onnx/onnx_converter.py
mgeconvert/backend/ir_to_onnx/onnx_op.py
mgeconvert/backend/ir_to_tflite/__init__.py
mgeconvert/backend/ir_to_tflite/build_flatbuffer.sh
mgeconvert/backend/ir_to_tflite/init.sh
mgeconvert/backend/ir_to_tflite/tflite_converter.py
mgeconvert/backend/ir_to_tflite/tflite_op.py
mgeconvert/backend/ir_to_tflite/pyflexbuffers/__init__.py
mgeconvert/backend/ir_to_tflite/pyflexbuffers/fbconverter.cc
mgeconvert/backend/ir_to_tflite/pyflexbuffers/fbconverter.so
mgeconvert/backend/ir_to_tflite/pyflexbuffers/bin/flatc
mgeconvert/backend/ir_to_tflite/pyflexbuffers/include/flatbuffers/base.h
mgeconvert/backend/ir_to_tflite/pyflexbuffers/include/flatbuffers/code_generators.h
mgeconvert/backend/ir_to_tflite/pyflexbuffers/include/flatbuffers/flatbuffers.h
mgeconvert/backend/ir_to_tflite/pyflexbuffers/include/flatbuffers/flatc.h
mgeconvert/backend/ir_to_tflite/pyflexbuffers/include/flatbuffers/flexbuffers.h
mgeconvert/backend/ir_to_tflite/pyflexbuffers/include/flatbuffers/grpc.h
mgeconvert/backend/ir_to_tflite/pyflexbuffers/include/flatbuffers/hash.h
mgeconvert/backend/ir_to_tflite/pyflexbuffers/include/flatbuffers/idl.h
mgeconvert/backend/ir_to_tflite/pyflexbuffers/include/flatbuffers/minireflect.h
mgeconvert/backend/ir_to_tflite/pyflexbuffers/include/flatbuffers/reflection.h
