Metadata-Version: 1.1
Name: mgeconvert
Version: 1.0.2
Summary: MegEngine Converter
Home-page: https://github.com/MegEngine/mgeconvert
Author: Megvii Engine Team
Author-email: brain-engine@megvii.com
License: UNKNOWN
Platform: UNKNOWN
Classifier: Programming Language :: Python :: 3
Classifier: License :: OSI Approved :: MIT License
Classifier: Operating System :: OS Independent
